{
    "Id" : 13,
    "Type" : "Anime SubThai",
    "Name" : "Peter Grill to Kenja no Jikan",
    "Category" : "BD [1080P]",
    "Chapter" : "1-4",
    "CheckChapter" : "OnGoing",
    "Trans" : {"Trans" : "Nemuria-Fansub", "Link" : "https://www.facebook.com/NeMuRiaPresent"},
    "Story" : ["Hentai","18+","Love"],
    "Download" : [
        {
            "EP" : "Peter Grill to Kenja no Jikan - 01 [BD]",
            "Dowload" : [
                {"Name" : "MP4","Link" : "https://mega.nz/file/C8cU0BxY#8nrv6MpwN2UEfOjipRIqxpcl9H51Lo3uwIxqELiNmlM"}
            ]
        },
        {
            "EP" : "Peter Grill to Kenja no Jikan - 02 [BD]",
            "Dowload" : [
                {"Name" : "MP4","Link" : "https://mega.nz/file/SgUSwTQB#jKAat_VnOry_fvC89n7H2rd3XpeM9_vXw1iKn5Vzg1U"}
            ]
        },
        {
            "EP" : "Peter Grill to Kenja no Jikan - 03 [BD]",
            "Dowload" : [
                {"Name" : "MP4","Link" : "https://mega.nz/file/W9EUkTSR#qEq-j1h0SUQhxLLWQJQTv_iZ8jrk__MqG3UkPk0Jmd8"}
            ]
        },
        {
            "EP" : "Peter Grill to Kenja no Jikan - 04 [BD]",
            "Dowload" : [
                {"Name" : "MP4","Link" : "https://mega.nz/file/7wVAjLqI#n_uZCYeNugshtGYKd4JHNXTEYsiPTIRU7Il0pRAsTig"}
            ]
        },
        {
            "EP" : "Peter Grill to Kenja no Jikan - 05 [BD]",
            "Dowload" : [
                {"Name" : "MP4","Link" : "https://mega.nz/file/jR1mwJDZ#wz7s_0AkBXm-QWqgzxcV5AkK2fVWwh_fOYTgI1effy8"}
            ]
        },
        {
            "EP" : "Peter Grill to Kenja no Jikan - 06 [BD]",
            "Dowload" : [
                {"Name" : "MP4","Link" : "https://mega.nz/file/zdFAWZgI#EblOwKP_YgWUdmdfMHjFT2Wtb-7_83ynoQxQOQ-Kyso"}
            ]
        },
        {
            "EP" : "Peter Grill to Kenja no Jikan - 07 [BD]",
            "Dowload" : [
                {"Name" : "MP4","Link" : "https://mega.nz/file/Kdl2AT4R#JYqn7HAk15m_f5IER0VBPhQKkH7eAdBqEVqbtviDxjk"}
            ]
        },
        {
            "EP" : "Peter Grill to Kenja no Jikan - 08 [BD]",
            "Dowload" : [
                {"Name" : "MP4","Link" : "https://mega.nz/file/jY9SHDZK#moeC9IRNoR6LRHFzjIE6n8bbP18JLSmVlMWiNbJxaJI"}
            ]
        },
        {
            "EP" : "Peter Grill to Kenja no Jikan - 09 [BD]",
            "Dowload" : [
                {"Name" : "MP4","Link" : "https://mega.nz/file/GAkGDLAB#Dk5-SY4nAiRmIYGWzlMniGATuCadOtadWUJL0nGOkWY"}
            ]
        },
        {
            "EP" : "Peter Grill to Kenja no Jikan - 10 [BD]",
            "Dowload" : [
                {"Name" : "MP4","Link" : "https://mega.nz/file/bUNQUJRJ#8550mFEpVun_DHRQca0Z6-2FeiRbreqMb7piAkPgfSM"}
            ]
        },
        {
            "EP" : "Peter Grill to Kenja no Jikan - 11 [BD]",
            "Dowload" : [
                {"Name" : "MP4","Link" : "https://mega.nz/file/qIkiCR7L#4GU_6qImX-4DcQs3ZDtaVc9j1s77RnOpXg9eS-bGWJg"}
            ]
        },
        {
            "EP" : "Peter Grill to Kenja no Jikan - 12 [BD][END]",
            "Dowload" : [
                {"Name" : "MP4","Link" : "https://mega.nz/file/3Q9mwRZa#UbrJyqtwhBKatYhVPEVuaimvBG4Ed9k-25esFQbcKo4"}
            ]
        }
    ],
    "Description" : "พระเอกเรานั้นได้ชนะเลิศแล้วเป็นผู้แข็งแกร่งของโลกใบนี้ ซึ่งพระเอกนั้นมีแฟนอยู่ แต่กลับเป็นว่าพวกคนในเมืองอื่นๆก็อยากได้น้ำเชื่อพระเอกไปเพื่อมีลูก",
    "Picture" : "https://sv1.picz.in.th/images/2020/12/07/jiycjg.jpg"
}